.readthedocs.yml
.readthedocs_env.yml
CHANGELOG.md
LICENSE
MANIFEST.in
README.md
pyproject.toml
setup.py
docs/Makefile
docs/source/about.rst
docs/source/conf.py
docs/source/index.rst
docs/source/requirements.txt
docs/source/section-cli.rst
docs/source/section-viz.rst
docs/source/_static/pwkit.css
docs/source/_templates/layout.html
docs/source/_templates/page.html
docs/source/cli-tools/index.rst
docs/source/cli-tools/pwkit-cli-multitool.rst
docs/source/cli-tools/pwkit-cli-toplevel.rst
docs/source/cli-tools/pwkit-kwargv.rst
docs/source/environments/index.rst
docs/source/environments/casa/dftdynspec.rst
docs/source/environments/casa/dftphotom.rst
docs/source/environments/casa/index.rst
docs/source/environments/casa/tasks.rst
docs/source/environments/casa/utilities.rst
docs/source/environments/heasoft/index.rst
docs/source/environments/sas/data.rst
docs/source/environments/sas/index.rst
docs/source/foundations/core.rst
docs/source/foundations/index.rst
docs/source/foundations/io.rst
docs/source/foundations/numerical.rst
docs/source/foundations/parallel.rst
docs/source/foundations/pwkit-simpleenum.rst
docs/source/infrastructure/index.rst
docs/source/infrastructure/pwkit-environments-toplevel.rst
docs/source/infrastructure/pwkit-method_decorator.rst
docs/source/io/index.rst
docs/source/io/pwkit-inifile.rst
docs/source/io/pwkit-latex.rst
docs/source/io/pwkit-tabfile.rst
docs/source/io/pwkit-tinifile.rst
docs/source/io/pwkit-unicode_to_latex.rst
docs/source/io/slurp.rst
docs/source/pwkit/colormaps.rst
docs/source/pwkit/contours.rst
docs/source/pwkit/data_gui_helpers.rst
docs/source/pwkit/ndshow_gtk3.rst
docs/source/pwkit/cli/astrotool.rst
docs/source/pwkit/cli/imtool.rst
docs/source/pwkit/cli/latexdriver.rst
docs/source/pwkit/cli/wrapout.rst
docs/source/pwkit/environments/casa/scripting.rst
docs/source/pwkit/environments/casa/spwglue.rst
docs/source/pwkit/environments/ciao/index.rst
docs/source/science/basic-astro.rst
docs/source/science/dulk-models.rst
pwkit.egg-info/PKG-INFO
pwkit.egg-info/SOURCES.txt
pwkit.egg-info/dependency_links.txt
pwkit.egg-info/entry_points.txt
pwkit.egg-info/not-zip-safe
pwkit.egg-info/requires.txt
pwkit.egg-info/top_level.txt
